cli/README.md
cli/__init__.py
cli/cli.py
cli/commands/__init__.py
cli/commands/config_cmd.py
cli/commands/development_cmd.py
cli/commands/list_cmd.py
cli/commands/mcp_cmd.py
cli/utils.py
codemie/__init__.py
codemie/client.py
codemie/generated/proto/v1/service_pb2.py
codemie/generated/proto/v1/service_pb2.pyi
codemie/langchain/__init__.py
codemie/langchain/services.py
codemie/logging.py
codemie/toolkit.py
toolkits/__init__.py
toolkits/core/__init__.py
toolkits/core/file_system_tools.py
toolkits/core/tools_vars.py
toolkits/core/utils.py
toolkits/development/__init__.py
toolkits/development/main.py
toolkits/development/process-compose.yml
toolkits/development/service/__init__.py
toolkits/development/service/diff_update_coder.py
toolkits/development/service/diff_update_prompts.py
toolkits/development/service/git_service.py
toolkits/development/toolkit.py
toolkits/development/tools.py
toolkits/development/tools_vars.py
toolkits/example/main.py
toolkits/example/process-compose.yml
toolkits/example/toolkit.py
toolkits/example/tools.py
toolkits/logs_analysis/main.py
toolkits/logs_analysis/parse_logs_tool.py
toolkits/logs_analysis/process-compose.yml
toolkits/logs_analysis/toolkit.py
toolkits/logs_analysis/tools_vars.py
toolkits/mcp/main.py
toolkits/mcp/process-compose.yml
toolkits/mcp/servers-win.json
toolkits/mcp/servers.json
toolkits/notification/main.py
toolkits/notification/process-compose.yml
toolkits/notification/toolkit.py
toolkits/notification/tools.py
toolkits/notification/tools_vars.py
codemie_plugins-0.1.133.dist-info/METADATA
codemie_plugins-0.1.133.dist-info/WHEEL
codemie_plugins-0.1.133.dist-info/entry_points.txt
codemie_plugins-0.1.133.dist-info/RECORD
