Metadata-Version: 2.1
Name: codemie-plugins
Version: 0.1.133
Summary: Command-line interface for running CodeMie Plugins toolkits
Author: CodeMie Team
Requires-Python: >=3.12,<4.0
Classifier: Programming Language :: Python :: 3
Classifier: Programming Language :: Python :: 3.12
Requires-Dist: click (==8.1.8)
Requires-Dist: gitpython (>=3.1.44,<4.0.0)
Requires-Dist: langchain (>=0.3.23,<0.4.0)
Requires-Dist: langchain-community (>=0.3.21,<0.4.0)
Requires-Dist: langchain-mcp-adapters (>=0.0.7,<0.0.8)
Requires-Dist: langchain-openai (>=0.3.12,<0.4.0)
Requires-Dist: langgraph (>=0.3.27,<0.4.0)
Requires-Dist: mcp (>=1.6.0,<2.0.0)
Requires-Dist: nats-py (==2.8.0)
Requires-Dist: pandas (>=2.2.3,<3.0.0)
Requires-Dist: protobuf (==5.27.3)
Requires-Dist: pydantic (>=2.11.3,<3.0.0)
Requires-Dist: pyfiglet (>=1.0.2,<2.0.0)
Requires-Dist: rich (==14.0.0)
